## 接口

### 接口的属性

所有接口的fields全部默认为public static final。尝试在接口的属性前面加入public static final，IDEA会自动暗化修饰符。
并且尝试直接调用属性，可以成功打印。值得注意地是所有的成员变量都必须显示初始化。这里比较好理解，因为所有的变量都是final的，
而接口本身又不能实例化，没有显式初始化等于这个属性没有值。

### 接口中的方法

和属性类似，接口中的方法全部都是默认为public abstract。无法使用任何其他修饰进行修饰。由于接口不能被实例化，所以也不存在构造方法。
但是由于接口可以被不同的类实现，所以实现类可以通过构造器来间接实现一个接口。这个部分后面会通过反编译的结果来进行分析，接口到底有没有被实例化。

### 接口的继承与实现

接口只能被接口继承，而且不同于类的继承，接口可以被多个接口继承，也可以继承多个接口。 同时，接口也可以被多个不同的类实现。
但是接口不能实现一个接口。 这里的逻辑实际上简化一下就是，接口由于本身就是抽象的，所以它无法实现任何接口。但是类可以实例化，于是可以直接实现接口。
由于接口规定了实现它所需要的所有能力（方法），所以一个类必须实现所有方法才可以实现一个接口。一个简单的例子就是，充电插头，我可以使用很多不同的数据线，
但是规格必须能配上这个插头，不然就无法连接。这里还有一个注意点就是，实现类必须实现接口的所有功能，但是抽象类不需要。因为抽象类本身也是抽象的，
它虽然在代码中是实现接口(implements)，但是其实抽象类是由它的实现类来完成实现接口的。
> 1. 这里有意思的点是，抽象类由于不需要实现所有的功能，反而不需要在class中声明任何接口方法。因为实现类不能实现一个抽象类，只能继承。
     > 所以这里java的设计，我个人觉得还挺精妙的。因为这样保证类与接口直接的关系永远是实现，而类与类之间永远是继承，接口与接口永远是继承。
> 2. 不同接口中所有的属性也彼此独立，我尝试了给三个不同的接口使用一样的值和变量名name，三个接口是一一继承的关系，然后使用了一个抽象类实现了底层的接口，
     > 最后用实现类继承了抽象类。结果在实现类中打印所有的name的时候，发现所有的name都没有被覆盖。
> 3. 接口在java 8之后允许加入静态方法。这里有一个思考就是，既然我希望接口是一个抽象的东西，为什么我要在接口中接入一个具体方法，然后具体实现这个方法。
     > 个人感觉意义不大，可能是因为需要完成某些操作。
> 4. 接口在java 9之后甚至允许加入private method，并且可以直接在接口中实现。
> 5. 接口的多继承算是破解了java中单一继承的规则。

###  接口中的默认方法
从java 8之后，接口中可以通过写一个default方法来实现一个具体的方法。并且由于这个方法被实现了，所以实现类可以选择不重写这个方法。
所有实现或者继承这个接口的类或者接口都可以调用这个方法。和前面提到的private方法一样，在接口内部，default方法还可以调用private方法。

### 接口中的运行顺序
由于接口不能写入静态块，所以直接测试接口的顺序意义也不大，而且接口也不能被实例化，所以这个顺序问题算是一个小的分支。
```shell
 0 new #7 <interfaces/MyInterfaceImpl>
 3 dup
 4 invokespecial #9 <interfaces/MyInterfaceImpl.<init> : ()V>
 7 astore_1
 8 aload_1
 9 invokevirtual #10 <interfaces/MyAbstractClass.test : ()V>
12 aload_1
13 iconst_1
14 invokevirtual #13 <interfaces/MyAbstractClass.test2 : (I)V>
17 return
```
这个是实例化一个实现类得到的反编译结果，可以发现和预想的一样，由于接口不会被实例化，所以在具体构造一个实例的时候，并不会调用到接口，基本等于没有参与。

### 小节
接口和抽象类都提供了一种很好的程序设计思路。不同与抽象类，接口更为灵活，无论是多继承还是不需要实现具体类都给接口提供了很多不同的用法。
因为接口只需要规定具备能力，就可以通过很多不同的类去实现。这样做的好处是有效降低了耦合度，代码与代码之间不会过分共享某些变量，而是可以随意切换和插拔。
举一个简单列子，如果我看到某个餐厅（实例），在进店之前我并不知道它是卖什么的（方法），可如果它是某一品牌（接口）的分店，我就可以直接确认我要不要吃这个，
因为它一定具备某个招牌菜或者服务（实现接口）。当运用到编程中，就等于我不要在去考虑某一个类到底是干什么的，只要知道他实现了某个接口，我就可以判断它
一定可以干什么。那么这样不条理清晰而且容易理解。